Bard.py
GoogleBard1-2.1.4.dist-info/LICENSE
GoogleBard1-2.1.4.dist-info/METADATA
GoogleBard1-2.1.4.dist-info/WHEEL
GoogleBard1-2.1.4.dist-info/top_level.txt
GoogleBard1-2.1.4.dist-info/RECORD
