Metadata-Version: 2.1
Name: GoogleBard1
Version: 2.1.4
Summary: Reverse engineering of Google's Bard chatbot
Home-page: https://github.com/Simatwa/Bard
Author: Antonio Cheong
Author-email: acheong@student.dalat.org
Maintainer: Smartwa
Maintainer-email: simatwacaleb@proton.me
License: MIT License
Project-URL: Bug Report, https://github.com/Simatwa/Bard/issues/new
Classifier: License :: OSI Approved :: MIT License
Classifier: Intended Audience :: Developers
Classifier: Topic :: Software Development :: Libraries :: Python Modules
Classifier: Programming Language :: Python :: 3.8
Classifier: Programming Language :: Python :: 3.9
Classifier: Programming Language :: Python :: 3.10
Classifier: Programming Language :: Python :: 3.11
License-File: LICENSE
Requires-Dist: prompt-toolkit
Requires-Dist: rich
Requires-Dist: httpx[socks]
